esm_viz/__init__.py
esm_viz/cli.py
esm_viz/esm_viz.py
esm_viz/analysis/__init__.py
esm_viz/analysis/echam/monitoring_echam_global_climatology.sh
esm_viz/analysis/echam/monitoring_echam_global_timeseries.sh
esm_viz/analysis/echam/.ipynb_checkpoints/monitoring_echam_global_climatology-checkpoint.sh
esm_viz/analysis/fesom/monitoring_fesom_global_timeseries.sh
esm_viz/analysis/general/say_hello.sh
esm_viz/analysis/pism/monitoring_pism_timeseries.sh
esm_viz/deployment/__init__.py
esm_viz/deployment/generate_automatic_ssh_key.sh
esm_viz/deployment/.ipynb_checkpoints/Panel_Test-checkpoint.ipynb
esm_viz/visualization/__init__.py
esm_viz/visualization/echam.py
esm_viz/visualization/fesom.py
esm_viz/visualization/general.py
esm_viz/visualization/logfile.py
esm_viz/visualization/mini_example.py
esm_viz/visualization/pism.py
esm_viz/visualization/.ipynb_checkpoints/Untitled-checkpoint.ipynb
esm_viz/visualization/.ipynb_checkpoints/Untitled1-checkpoint.ipynb
esm_viz/visualization/.ipynb_checkpoints/Untitled2-checkpoint.ipynb
esm_viz/visualization/.ipynb_checkpoints/echam_global_climatology-checkpoint.ipynb
esm_viz/visualization/.ipynb_checkpoints/echam_global_timeseries-checkpoint.ipynb
esm_viz/visualization/.ipynb_checkpoints/general_disk_usage-checkpoint.ipynb
esm_viz/visualization/.ipynb_checkpoints/general_newest_log-checkpoint.ipynb
esm_viz/visualization/.ipynb_checkpoints/general_progress_bar-checkpoint.ipynb
esm_viz/visualization/.ipynb_checkpoints/general_queue_info-checkpoint.ipynb
esm_viz/visualization/.ipynb_checkpoints/general_run_efficiency-checkpoint.ipynb
esm_viz/visualization/.ipynb_checkpoints/general_simulation_timeline-checkpoint.ipynb
esm_viz/visualization/.ipynb_checkpoints/general_simulation_timeline-hvplot-checkpoint.ipynb
esm_viz/visualization/.ipynb_checkpoints/last_update-checkpoint.ipynb
esm_viz/visualization/.ipynb_checkpoints/pism_timeseries-checkpoint.ipynb
esm_viz/visualization/.ipynb_checkpoints/read_config-checkpoint.ipynb
esm_viz-0.9.7.dist-info/LICENSE
esm_viz-0.9.7.dist-info/METADATA
esm_viz-0.9.7.dist-info/WHEEL
esm_viz-0.9.7.dist-info/entry_points.txt
esm_viz-0.9.7.dist-info/top_level.txt
esm_viz-0.9.7.dist-info/RECORD
