Metadata-Version: 2.1
Name: esm-viz
Version: 0.9.7
Summary: esm-viz allows you to monitor and visualize ongoing simulations
Home-page: https://github.com/pgierz/esm_viz
Author: Paul Gierz
Author-email: pgierz@awi.de
License: GNU General Public License v3
Keywords: esm_viz
Platform: UNKNOWN
Classifier: Development Status :: 2 - Pre-Alpha
Classifier: Intended Audience :: Developers
Classifier: License :: OSI Approved :: GNU General Public License v3 (GPLv3)
Classifier: Natural Language :: English
Classifier: Programming Language :: Python :: 2
Classifier: Programming Language :: Python :: 2.7
Classifier: Programming Language :: Python :: 3
Classifier: Programming Language :: Python :: 3.4
Classifier: Programming Language :: Python :: 3.5
Classifier: Programming Language :: Python :: 3.6
Classifier: Programming Language :: Python :: 3.7
Requires-Dist: Click (>=6.0)
Requires-Dist: cartopy
Requires-Dist: cftime
Requires-Dist: cmocean
Requires-Dist: datashader
Requires-Dist: geoviews
Requires-Dist: holoviews
Requires-Dist: hvplot
Requires-Dist: numexpr (>=2.6.1)
Requires-Dist: numpy (>=1.12)
Requires-Dist: pandas (>=0.19.2)
Requires-Dist: panel
Requires-Dist: paramiko
Requires-Dist: pillow (>=4.0)
Requires-Dist: pyopenssl (>=19)
Requires-Dist: pyproj
Requires-Dist: python-crontab
Requires-Dist: pyyaml
Requires-Dist: setuptools (>=36)
Requires-Dist: shapely
Requires-Dist: tornado (>=5.0)
Requires-Dist: tqdm
Requires-Dist: xarray
